LICENSE
MANIFEST.in
README.rst
setup.py
google/__init__.py
google/cloud/__init__.py
google/cloud/proto/__init__.py
google/cloud/proto/vision/__init__.py
google/cloud/proto/vision/v1/__init__.py
google/cloud/proto/vision/v1/geometry_pb2.py
google/cloud/proto/vision/v1/geometry_pb2_grpc.py
google/cloud/proto/vision/v1/image_annotator_pb2.py
google/cloud/proto/vision/v1/image_annotator_pb2_grpc.py
google/cloud/proto/vision/v1/text_annotation_pb2.py
google/cloud/proto/vision/v1/text_annotation_pb2_grpc.py
google/cloud/proto/vision/v1/web_detection_pb2.py
google/cloud/proto/vision/v1/web_detection_pb2_grpc.py
proto_google_cloud_vision_v1.egg-info/PKG-INFO
proto_google_cloud_vision_v1.egg-info/SOURCES.txt
proto_google_cloud_vision_v1.egg-info/dependency_links.txt
proto_google_cloud_vision_v1.egg-info/namespace_packages.txt
proto_google_cloud_vision_v1.egg-info/requires.txt
proto_google_cloud_vision_v1.egg-info/top_level.txt